zu/__init__.py
zu/naming.py
zu/paths.py
zu/str_utils.py
zu/tuples.py
zu-0.0.2.dist-info/LICENSE
zu-0.0.2.dist-info/METADATA
zu-0.0.2.dist-info/WHEEL
zu-0.0.2.dist-info/top_level.txt
zu-0.0.2.dist-info/RECORD
