Metadata-Version: 2.1
Name: zu
Version: 0.0.2
Summary: Useful Layers for Data Access
Home-page: https://github.com/i2mint/zu
Author: OtoSense
License: mit
Platform: any
